neurone_loader/__init__.py
neurone_loader/lazy.py
neurone_loader/loader.py
neurone_loader/mne_export.py
neurone_loader/neurone.py
neurone_loader/util.py
neurone_loader-2.0.1.dist-info/LICENSE
neurone_loader-2.0.1.dist-info/METADATA
neurone_loader-2.0.1.dist-info/WHEEL
neurone_loader-2.0.1.dist-info/top_level.txt
neurone_loader-2.0.1.dist-info/RECORD
