Metadata-Version: 2.1
Name: neurone-loader
Version: 2.0.1
Summary: Utilities for loading data recorded with NeurOne
Home-page: http://github.com/heilerich/neurone_loader
Author: Felix Heilmeyer
Author-email: code@fehe.eu
License: MIT
Download-URL: https://github.com/heilerich/neurone_loader/archive/2.0.1.tar.gz
Keywords: EEG,science,neuroscience,neurone,bittium,megaemg,MNE
Platform: UNKNOWN
Classifier: License :: OSI Approved :: MIT License
Classifier: Programming Language :: Python :: 3.7
Classifier: Programming Language :: Python :: 3.8
Classifier: Programming Language :: Python :: 3.9
Classifier: Topic :: Scientific/Engineering
Requires-Python: >=2.7, !=3.0.*, !=3.1.*, !=3.2.*, !=3.3.*, !=3.4.*, !=3.5.*, !=3.6.*, <4
Requires-Dist: numpy (>=1.16.0)
Requires-Dist: pandas (>=0.23.4)
Requires-Dist: construct (>=2.9.45)
